ok_language_tools/__init__.py
ok_language_tools/apps.py
ok_language_tools/conf.py
ok_language_tools/middleware.py
ok_language_tools/urls.py
ok_language_tools/utils.py
ok_language_tools/views.py
ok_language_tools/migrations/__init__.py
django_ok_language_tools-0.0.4.dist-info/LICENSE
django_ok_language_tools-0.0.4.dist-info/METADATA
django_ok_language_tools-0.0.4.dist-info/WHEEL
django_ok_language_tools-0.0.4.dist-info/top_level.txt
django_ok_language_tools-0.0.4.dist-info/RECORD
