Metadata-Version: 2.1
Name: django-ok-language-tools
Version: 0.0.4
Summary: Some language tools for Django.
Home-page: https://github.com/LowerDeez/ok-language-tools
Author: Oleg Kleschunov
Author-email: igorkleschunov@gmail.com
License: MIT
Keywords: python,django,language,i18n
Platform: UNKNOWN
Classifier: Development Status :: 4 - Beta
Classifier: Environment :: Web Environment
Classifier: Intended Audience :: Developers
Classifier: License :: OSI Approved :: MIT License
Classifier: Operating System :: OS Independent
Classifier: Programming Language :: Python
Classifier: Programming Language :: Python :: 3.6
Classifier: Programming Language :: Python :: 3.7
Classifier: Programming Language :: Python :: 3.8
Classifier: Framework :: Django
Classifier: Framework :: Django :: 2.2
Classifier: Framework :: Django :: 3.1
Requires-Dist: django (>=2.2)
Requires-Dist: six
Requires-Dist: mock
